.gitignore
LICENSE
MANIFEST.in
README.md
requirements.txt
setup.py
curatedmetagenomicdata3/__init__.py
curatedmetagenomicdata3.egg-info/PKG-INFO
curatedmetagenomicdata3.egg-info/SOURCES.txt
curatedmetagenomicdata3.egg-info/dependency_links.txt
curatedmetagenomicdata3.egg-info/requires.txt
curatedmetagenomicdata3.egg-info/top_level.txt
curatedmetagenomicdata3/assets/pathways.csv
curatedmetagenomicdata3/assets/sampleMetadata.csv
curatedmetagenomicdata3/assets/sampleMetadata.pickle
curatedmetagenomicdata3/assets/taxa.txt
curatedmetagenomicdataextractor3/README.md
curatedmetagenomicdataextractor3/download/download_dataset.R
curatedmetagenomicdataextractor3/download/download_one_dataset.R