Metadata-Version: 1.1
Name: curatedmetagenomicdata3
Version: 0.1.4
Summary: Python wrapper for curatedMetagenomicData3.
Home-page: https://github.com/kellylab/curatedmetagenomidata3-python
Author: UNKNOWN
Author-email: skhan8@mail.einstein.yu.edu
License: UNKNOWN
Platform: UNKNOWN
Classifier: Programming Language :: Python :: 3
Classifier: License :: OSI Approved :: MIT License
Classifier: Operating System :: OS Independent
